spackager
