Metadata-Version: 1.0
Name: spackager
Version: 0.5.5
Summary: compiler for creating single-page applications
Home-page: http://pypi.python.org/pypi/spackager
Author: FND
Author-email: FNDo@gmx.net
License: UNKNOWN
Platform: Posix; MacOS X; Windows
